RequirementsLibrary/__init__.py
RequirementsLibrary/keywords.py
RequirementsLibrary/version.py
robotframework_requirements-0.1.0.dist-info/LICENSE
robotframework_requirements-0.1.0.dist-info/METADATA
robotframework_requirements-0.1.0.dist-info/WHEEL
robotframework_requirements-0.1.0.dist-info/top_level.txt
robotframework_requirements-0.1.0.dist-info/RECORD
