Metadata-Version: 2.1
Name: robotframework-requirements
Version: 0.1.0
Summary: RobotFramework library that verifies installed libraries against requirements.txt
Home-page: https://github.com/kivipe/robotframework-requirements
Author: Pekka Kiviniemi
Author-email: pekka.kiviniemi@ekivi.com
License: UNKNOWN
Project-URL: Bug Tracker, https://github.com/kivipe/robotframework-requirements/issues
Platform: UNKNOWN
Classifier: Development Status :: 3 - Alpha
Classifier: Programming Language :: Python :: 3
Classifier: License :: OSI Approved :: MIT License
Classifier: Operating System :: OS Independent
Requires-Python: >=3.6
License-File: LICENSE
